zotutil/__init__.py
zotutil/tools.py
zotutil/zot.py
zotutil-0.1.1.dist-info/AUTHORS.rst
zotutil-0.1.1.dist-info/LICENSE
zotutil-0.1.1.dist-info/METADATA
zotutil-0.1.1.dist-info/WHEEL
zotutil-0.1.1.dist-info/top_level.txt
zotutil-0.1.1.dist-info/RECORD
